agoraapi/__init__.py
agoraapi/account/__init__.py
agoraapi/account/v3/__init__.py
agoraapi/account/v3/account_service_pb2.py
agoraapi/account/v3/account_service_pb2_grpc.py
agoraapi/account/v4/__init__.py
agoraapi/account/v4/account_service_pb2.py
agoraapi/account/v4/account_service_pb2_grpc.py
agoraapi/airdrop/__init__.py
agoraapi/airdrop/v4/__init__.py
agoraapi/airdrop/v4/airdrop_service_pb2.py
agoraapi/airdrop/v4/airdrop_service_pb2_grpc.py
agoraapi/common/__init__.py
agoraapi/common/v3/__init__.py
agoraapi/common/v3/model_pb2.py
agoraapi/common/v3/model_pb2_grpc.py
agoraapi/common/v4/__init__.py
agoraapi/common/v4/model_pb2.py
agoraapi/common/v4/model_pb2_grpc.py
agoraapi/metrics/__init__.py
agoraapi/metrics/v3/__init__.py
agoraapi/metrics/v3/ingestion_service_pb2.py
agoraapi/metrics/v3/ingestion_service_pb2_grpc.py
agoraapi/metrics/v3/model_pb2.py
agoraapi/metrics/v3/model_pb2_grpc.py
agoraapi/transaction/__init__.py
agoraapi/transaction/v3/__init__.py
agoraapi/transaction/v3/transaction_service_pb2.py
agoraapi/transaction/v3/transaction_service_pb2_grpc.py
agoraapi/transaction/v4/__init__.py
agoraapi/transaction/v4/transaction_service_pb2.py
agoraapi/transaction/v4/transaction_service_pb2_grpc.py
agoraapi/validate/__init__.py
agoraapi/validate/validate_pb2.py
agoraapi/validate/validate_pb2_grpc.py
agora_api-0.26.0.dist-info/METADATA
agora_api-0.26.0.dist-info/WHEEL
agora_api-0.26.0.dist-info/top_level.txt
agora_api-0.26.0.dist-info/RECORD
