Metadata-Version: 2.1
Name: agora-api
Version: 0.26.0
Summary: Agora API for Python
Home-page: https://github.com/kinecosystem/agora-api
Author: Kik Engineering
Author-email: engineering@kik.com
License: MIT
Platform: UNKNOWN
Classifier: License :: OSI Approved :: MIT License
Classifier: Intended Audience :: Developers
Classifier: Topic :: Software Development :: Libraries :: Python Modules
Classifier: Programming Language :: Python
Classifier: Programming Language :: Python :: 3
